raadpy/__init__.py
raadpy/core.py
raadpy/event.py
raadpy/functionality.py
raadpy/plotting.py
raadpy/rparray.py
raadpy-2.1.5.dist-info/LICENSE
raadpy-2.1.5.dist-info/METADATA
raadpy-2.1.5.dist-info/WHEEL
raadpy-2.1.5.dist-info/top_level.txt
raadpy-2.1.5.dist-info/RECORD
