Metadata-Version: 2.1
Name: raadpy
Version: 2.1.5
Summary: Python wrapper for data analysis of the RAAD detector
Home-page: https://github.com/nyuad-astroparticle/raadpy
Author: NYUAD Astroparticle Lab (Panos Oikonomou, Danish Khan, Lolowa AlKindi)
Author-email: po524@nyu.edu
Project-URL: Bug Tracker, https://github.com/nyuad-astroparticle/raadpy/issues
Classifier: Development Status :: 3 - Alpha
Classifier: Programming Language :: Python :: 3
Classifier: License :: OSI Approved :: MIT License
Classifier: Operating System :: OS Independent
Requires-Python: >=3.6
License-File: LICENSE
Requires-Dist: matplotlib (>=3.5.1)
Requires-Dist: numpy (>=1.22.3)
Requires-Dist: astropy (>=5.0.2)
Requires-Dist: pandas (>=1.4.1)
Requires-Dist: requests (>=2.27.1)
Requires-Dist: requests-oauthlib (>=1.0.0)
Requires-Dist: tqdm (>=4.64)
Requires-Dist: lxml (>=4.8.0)
Requires-Dist: plotly (>=5.8.2)
Requires-Dist: sshtunnel (>=0.4.0)
Requires-Dist: pymysql (>=1.0.2)
Requires-Dist: IPython (>=1.0.0)
